tiledb/bioimg/__init__.py
tiledb/bioimg/helpers.py
tiledb/bioimg/openslide.py
tiledb/bioimg/types.py
tiledb/bioimg/version.py
tiledb/bioimg/wrappers.py
tiledb/bioimg/converters/__init__.py
tiledb/bioimg/converters/axes.py
tiledb/bioimg/converters/base.py
tiledb/bioimg/converters/metadata.py
tiledb/bioimg/converters/ome_tiff.py
tiledb/bioimg/converters/ome_zarr.py
tiledb/bioimg/converters/openslide.py
tiledb/bioimg/converters/scale.py
tiledb/bioimg/converters/tiles.py
tiledb_bioimg-0.12.15.dist-info/LICENSE
tiledb_bioimg-0.12.15.dist-info/METADATA
tiledb_bioimg-0.12.15.dist-info/WHEEL
tiledb_bioimg-0.12.15.dist-info/top_level.txt
tiledb_bioimg-0.12.15.dist-info/RECORD
