Metadata-Version: 2.1
Name: tiledb-bioimg
Version: 0.12.15
Summary: Package supports all bio-imaging functionality provided by TileDB
Home-page: https://github.com/TileDB-Inc/TileDB-Bioimaging
Author: TileDB, Inc.
Author-email: help@tiledb.io
License: MIT
Project-URL: Bug Tracker, https://github.com/TileDB-Inc/TileDB-Bioimaging/issues
Project-URL: Documentation, https://docs.tiledb.com
Keywords: tiledb,bioimaging
Platform: any
Classifier: Development Status :: 2 - Pre-Alpha
Classifier: Intended Audience :: Developers
Classifier: Intended Audience :: Information Technology
Classifier: Intended Audience :: Science/Research
Classifier: Programming Language :: Python
Classifier: Topic :: Software Development :: Libraries :: Python Modules
Classifier: Topic :: Scientific/Engineering :: Bio-Informatics
Classifier: Topic :: Scientific/Engineering :: Image Processing
Classifier: Operating System :: Unix
Classifier: Operating System :: POSIX :: Linux
Classifier: Operating System :: MacOS :: MacOS X
Classifier: Programming Language :: Python :: 3
Classifier: Programming Language :: Python :: 3.7
Classifier: Programming Language :: Python :: 3.8
Classifier: License :: OSI Approved :: MIT License
Requires-Python: >=3.7
License-File: LICENSE
Requires-Dist: pyeditdistance
Requires-Dist: tiledb >=0.19
Requires-Dist: tqdm
Requires-Dist: scikit-image
Requires-Dist: jsonpickle
Requires-Dist: requires
Provides-Extra: cloud
Requires-Dist: tiledb-cloud ; extra == 'cloud'
Provides-Extra: full
Requires-Dist: imagecodecs ; extra == 'full'
Requires-Dist: ome-zarr >=0.9.0 ; extra == 'full'
Requires-Dist: openslide-python ; extra == 'full'
Requires-Dist: tifffile ; extra == 'full'
Provides-Extra: openslide
Requires-Dist: openslide-python ; extra == 'openslide'
Provides-Extra: tiff
Requires-Dist: tifffile ; extra == 'tiff'
Requires-Dist: imagecodecs ; extra == 'tiff'
Provides-Extra: zarr
Requires-Dist: ome-zarr >=0.9.0 ; extra == 'zarr'
